asyncio_rlock/__init__.py
asyncio_rlock-0.1.0.dist-info/LICENSE
asyncio_rlock-0.1.0.dist-info/METADATA
asyncio_rlock-0.1.0.dist-info/WHEEL
asyncio_rlock-0.1.0.dist-info/top_level.txt
asyncio_rlock-0.1.0.dist-info/RECORD
